[
    {
        "id":1,
        "tieuDe":"Tin so 1",
        "trichDan":"Hàng trăm người dân được yêu cầu sơ tán trong khoảng hơn một giờ để lực lượng quân đội di dời quả bom nặng 340 kg, đêm 29/11.",
        "noiDung":"Tối 29/11, Lực lượng chức năng lập hàng rào bán kính 200 m trên các phố Cửa Bắc, Phó Đức Chính, Phạm Hồng Thái và Nguyễn Trường Tộ (phường Trúc Bạch) để phục vụ di dời quả bom được phát hiện ở công tường xây dựng số 15 phố Cửa Bắc một ngày trước. Nhà chức trách yêu cầu người dân không sử dụng điện thoại, bộ đàm trong khu vưc này.",
        "anh":"https://i1-vnexpress.vnecdn.net/2020/11/30/16fd153aa81e5940000f-1606693296.jpg?w=1200&h=0&q=100&dpr=1&fit=crop&s=SOy6hsLSXMWxCZKQnQ5RJQ"
    },
    {
        "id":2,
        "tieuDe":"Tin so 2",
        "trichDan":"Sau ba năm khởi công, đường nối từ tuyến Phạm Văn Đồng đến nút giao Gò Dưa, quận Thủ Đức gần 3 km dang dở do chưa được thanh toán chi phí, chờ điều chỉnh dự án.",
        "noiDung":"Đây là một trong 4 đoạn chưa khép kín thuộc dự án Vành đai 2 TP HCM, khởi công cuối năm 2017 với tổng đầu tư hơn 2.500 tỷ đồng. Trong đó, chi phí giải phóng mặt bằng 1.410 tỷ đồng, tách thành dự án riêng do quận Thủ Đức triển khai. Dự án đầu tư theo hình thức BT (xây dựng - chuyển giao), do Công ty cổ phần Văn Phú Bắc Ái làm nhà đầu tư.",
        "anh":"https://i1-vnexpress.vnecdn.net/2020/11/29/Sequence0100004114Still001-149-1853-6284-1606661629.jpg?w=680&h=0&q=100&dpr=1&fit=crop&s=O0khnJe42woVv6_iSnCIVw"
    },
    {
        "id":3,
        "tieuDe":"Tin so 3",
        "trichDan":"Hàng trăm người dân được yêu cầu sơ tán trong khoảng hơn một giờ để lực lượng quân đội di dời quả bom nặng 340 kg, đêm 29/11.",
        "noiDung":"Tối 29/11, Lực lượng chức năng lập hàng rào bán kính 200 m trên các phố Cửa Bắc, Phó Đức Chính, Phạm Hồng Thái và Nguyễn Trường Tộ (phường Trúc Bạch) để phục vụ di dời quả bom được phát hiện ở công tường xây dựng số 15 phố Cửa Bắc một ngày trước. Nhà chức trách yêu cầu người dân không sử dụng điện thoại, bộ đàm trong khu vưc này.",
        "anh":"https://i1-vnexpress.vnecdn.net/2020/11/30/fbcapdoikoronoiosbrazilianosok-7118-4713-1606692904.jpg?w=680&h=408&q=100&dpr=1&fit=crop&s=YM-oMmEW7Ns1s8WSJO7adQ"
    },
    {
        "id":4,
        "tieuDe":"Tin so 4",
        "trichDan":"Hàng trăm người dân được yêu cầu sơ tán trong khoảng hơn một giờ để lực lượng quân đội di dời quả bom nặng 340 kg, đêm 29/11.",
        "noiDung":"Tối 29/11, Lực lượng chức năng lập hàng rào bán kính 200 m trên các phố Cửa Bắc, Phó Đức Chính, Phạm Hồng Thái và Nguyễn Trường Tộ (phường Trúc Bạch) để phục vụ di dời quả bom được phát hiện ở công tường xây dựng số 15 phố Cửa Bắc một ngày trước. Nhà chức trách yêu cầu người dân không sử dụng điện thoại, bộ đàm trong khu vưc này.",
        "anh":"https://i1-vnexpress.vnecdn.net/2020/11/29/2trump-newsletter-xxx-1-6404-1606668240.jpg?w=680&h=0&q=100&dpr=1&fit=crop&s=vB_PeNhyCq8_IxLyg8SkbQ"
    },
    {
        "id":5,
        "tieuDe":"Tin so 5",
        "trichDan":"Hàng trăm người dân được yêu cầu sơ tán trong khoảng hơn một giờ để lực lượng quân đội di dời quả bom nặng 340 kg, đêm 29/11.",
        "noiDung":"Tối 29/11, Lực lượng chức năng lập hàng rào bán kính 200 m trên các phố Cửa Bắc, Phó Đức Chính, Phạm Hồng Thái và Nguyễn Trường Tộ (phường Trúc Bạch) để phục vụ di dời quả bom được phát hiện ở công tường xây dựng số 15 phố Cửa Bắc một ngày trước. Nhà chức trách yêu cầu người dân không sử dụng điện thoại, bộ đàm trong khu vưc này.",
        "anh":"https://i1-vnexpress.vnecdn.net/2020/11/29/VnE-deokhanhle-A1-6106-1606655224.jpg?w=680&h=0&q=100&dpr=1&fit=crop&s=673gCiCvsWCMbELQSAolmA"
    },
    {
        "id":6,
        "tieuDe":"Tin so 6",
        "trichDan":"Hàng trăm người dân được yêu cầu sơ tán trong khoảng hơn một giờ để lực lượng quân đội di dời quả bom nặng 340 kg, đêm 29/11.",
        "noiDung":"Tối 29/11, Lực lượng chức năng lập hàng rào bán kính 200 m trên các phố Cửa Bắc, Phó Đức Chính, Phạm Hồng Thái và Nguyễn Trường Tộ (phường Trúc Bạch) để phục vụ di dời quả bom được phát hiện ở công tường xây dựng số 15 phố Cửa Bắc một ngày trước. Nhà chức trách yêu cầu người dân không sử dụng điện thoại, bộ đàm trong khu vưc này.",
        "anh":"https://i1-giadinh.vnecdn.net/2020/11/29/763-1606666843-4069-1606668093.jpg?w=680&h=0&q=100&dpr=1&fit=crop&s=BQCSw8UUIQjgjdawgLJnXw"
    },
    {
        "id":7,
        "tieuDe":"Tin so 7",
        "trichDan":"Hàng trăm người dân được yêu cầu sơ tán trong khoảng hơn một giờ để lực lượng quân đội di dời quả bom nặng 340 kg, đêm 29/11.",
        "noiDung":"Tối 29/11, Lực lượng chức năng lập hàng rào bán kính 200 m trên các phố Cửa Bắc, Phó Đức Chính, Phạm Hồng Thái và Nguyễn Trường Tộ (phường Trúc Bạch) để phục vụ di dời quả bom được phát hiện ở công tường xây dựng số 15 phố Cửa Bắc một ngày trước. Nhà chức trách yêu cầu người dân không sử dụng điện thoại, bộ đàm trong khu vưc này.",
        "anh":"https://i1-giadinh.vnecdn.net/2020/11/29/763-1606666843-4069-1606668093.jpg?w=680&h=0&q=100&dpr=1&fit=crop&s=BQCSw8UUIQjgjdawgLJnXw"
    },
    {
        "id":8,
        "tieuDe":"Tin so 8",
        "trichDan":"Hàng trăm người dân được yêu cầu sơ tán trong khoảng hơn một giờ để lực lượng quân đội di dời quả bom nặng 340 kg, đêm 29/11.",
        "noiDung":"Tối 29/11, Lực lượng chức năng lập hàng rào bán kính 200 m trên các phố Cửa Bắc, Phó Đức Chính, Phạm Hồng Thái và Nguyễn Trường Tộ (phường Trúc Bạch) để phục vụ di dời quả bom được phát hiện ở công tường xây dựng số 15 phố Cửa Bắc một ngày trước. Nhà chức trách yêu cầu người dân không sử dụng điện thoại, bộ đàm trong khu vưc này.",
        "anh":"https://i1-giadinh.vnecdn.net/2020/11/29/763-1606666843-4069-1606668093.jpg?w=680&h=0&q=100&dpr=1&fit=crop&s=BQCSw8UUIQjgjdawgLJnXw"
    },
    {
        "id":9,
        "tieuDe":"Tin so 9",
        "trichDan":"Hàng trăm người dân được yêu cầu sơ tán trong khoảng hơn một giờ để lực lượng quân đội di dời quả bom nặng 340 kg, đêm 29/11.",
        "noiDung":"Tối 29/11, Lực lượng chức năng lập hàng rào bán kính 200 m trên các phố Cửa Bắc, Phó Đức Chính, Phạm Hồng Thái và Nguyễn Trường Tộ (phường Trúc Bạch) để phục vụ di dời quả bom được phát hiện ở công tường xây dựng số 15 phố Cửa Bắc một ngày trước. Nhà chức trách yêu cầu người dân không sử dụng điện thoại, bộ đàm trong khu vưc này.",
        "anh":"https://i1-giadinh.vnecdn.net/2020/11/29/763-1606666843-4069-1606668093.jpg?w=680&h=0&q=100&dpr=1&fit=crop&s=BQCSw8UUIQjgjdawgLJnXw"
    },
    {
        "id":10,
        "tieuDe":"Tin so 10",
        "trichDan":"Hàng trăm người dân được yêu cầu sơ tán trong khoảng hơn một giờ để lực lượng quân đội di dời quả bom nặng 340 kg, đêm 29/11.",
        "noiDung":"Tối 29/11, Lực lượng chức năng lập hàng rào bán kính 200 m trên các phố Cửa Bắc, Phó Đức Chính, Phạm Hồng Thái và Nguyễn Trường Tộ (phường Trúc Bạch) để phục vụ di dời quả bom được phát hiện ở công tường xây dựng số 15 phố Cửa Bắc một ngày trước. Nhà chức trách yêu cầu người dân không sử dụng điện thoại, bộ đàm trong khu vưc này.",
        "anh":"https://i1-giadinh.vnecdn.net/2020/11/29/763-1606666843-4069-1606668093.jpg?w=680&h=0&q=100&dpr=1&fit=crop&s=BQCSw8UUIQjgjdawgLJnXw"
    }
]